charachorder/__init__.py
charachorder/__main__.py
charachorder/_types.py
charachorder/device.py
charachorder/errors.py
charachorder/py.typed
charachorder_py-0.6.0.dist-info/licenses/LICENSE
charachorder_py-0.6.0.dist-info/METADATA
charachorder_py-0.6.0.dist-info/WHEEL
charachorder_py-0.6.0.dist-info/top_level.txt
charachorder_py-0.6.0.dist-info/RECORD
