Metadata-Version: 2.4
Name: charachorder.py
Version: 0.6.0
Summary: A wrapper for CharaChorder's Serial API written in Python
Home-page: https://github.com/CharaChorder/charachorder.py
Author: GetPsyched
Author-email: dev@getpsyched.dev
License: MIT
Project-URL: Documentation, https://charachorder.github.io/charachorder.py
Project-URL: Issue tracker, https://github.com/CharaChorder/charachorder.py/issues
Classifier: License :: OSI Approved :: MIT License
Classifier: Intended Audience :: Developers
Classifier: Natural Language :: English
Classifier: Operating System :: OS Independent
Classifier: Programming Language :: Python :: 3.9
Classifier: Programming Language :: Python :: 3.10
Classifier: Programming Language :: Python :: 3.11
Classifier: Programming Language :: Python :: 3.12
Classifier: Topic :: Software Development :: Libraries
Classifier: Topic :: Software Development :: Libraries :: Python Modules
Classifier: Topic :: Utilities
Classifier: Typing :: Typed
Requires-Python: >=3.9.0
License-File: LICENSE
Requires-Dist: inquirer
Requires-Dist: pyserial
Dynamic: author
Dynamic: author-email
Dynamic: classifier
Dynamic: description
Dynamic: description-content-type
Dynamic: home-page
Dynamic: license
Dynamic: license-file
Dynamic: project-url
Dynamic: requires-dist
Dynamic: requires-python
Dynamic: summary
